djc_heroicons/__init__.py
djc_heroicons/app_settings.py
djc_heroicons/apps.py
djc_heroicons/icons.py
djc_heroicons/py.typed
djc_heroicons/utils.py
djc_heroicons/components/__init__.py
djc_heroicons/components/icon.py
djc_heroicons-1.1.0.dist-info/licenses/LICENSE
djc_heroicons-1.1.0.dist-info/METADATA
djc_heroicons-1.1.0.dist-info/WHEEL
djc_heroicons-1.1.0.dist-info/top_level.txt
djc_heroicons-1.1.0.dist-info/RECORD
