Metadata-Version: 2.4
Name: djc_heroicons
Version: 1.1.0
Summary: Icons from HeroIcons.com for django-components
Author-email: Juro Oravec <juraj.oravec.josefson@gmail.com>
License: MIT
Project-URL: Homepage, https://github.com/JuroOravec/djc-heroicons/
Keywords: django,components,heroicons,icon,component,html
Classifier: Framework :: Django
Classifier: Framework :: Django :: 4.2
Classifier: Framework :: Django :: 5.0
Classifier: Operating System :: OS Independent
Classifier: Programming Language :: Python
Classifier: Programming Language :: Python :: 3
Classifier: Programming Language :: Python :: 3.8
Classifier: Programming Language :: Python :: 3.9
Classifier: Programming Language :: Python :: 3.10
Classifier: Programming Language :: Python :: 3.11
Classifier: Programming Language :: Python :: 3.12
Requires-Python: <4.0,>=3.8
License-File: LICENSE
Requires-Dist: Django>=4.2
Requires-Dist: django-components>=0.140
Dynamic: license-file
